<?xml version="1.0" encoding="UTF-8"?>
<base xmlns:xsi="http://www.w3.org/2001/XMLSchema-instance" xmlns:xsd="http://www.w3.org/2001/XMLSchema" type="string">
 <strings>
  <string id="huaxia_jh_recruit" text="Huaxia Jianghu Recruit"/>
  <string id="huaxia_jh_infantry_1" text="Huaxia Wandering Swordsmen"/>
  <string id="huaxia_jh_infantry_2" text="Huaxia Jianghu Enforcer"/>
  <string id="huaxia_jh_infantry_3" text="Huaxia Jianghu Marauder"/>
  <string id="huaxia_jh_infantry_2a" text="Huaxia Jianghu Assassin"/>
  <string id="huaxia_jh_archer_1" text="Huaxia Forest Hunter"/>
  <string id="huaxia_jh_archer_2" text="Huaxia Field Ranger"/>
  <string id="huaxia_jh_archer_3" text="Huaxia Tiger Hunter"/>
 </strings>
</base>
