<?xml version="1.0" encoding="UTF-8"?>
<base xmlns:xsi="http://www.w3.org/2001/XMLSchema-instance" xmlns:xsd="http://www.w3.org/2001/XMLSchema" type="string">
 <strings>
  <string id="Fadecloak1" text="{.Nijaki}Pokryva Źniknieńnia"/>
  <string id="Fadearmor1" text="{.Zanocy}Brania Źniknieńnia (Nie apranajcie šałom z hetym pradmietam)"/>
  <string id="Fade2021fullbody" text="{.Nijaki}Cieła Źniknieńnia (Nie apranajcie šałom z hetym pradmietam)"/>
  <string id="TrollocBow" text="{.Muzcynski}Trołłaski Łuk"/>
  <string id="fadehands1" text="{.Mnozny}Trołłaskija Rukavicy"/>
  <string id="TrollocLight2" text="{.Nijaki}Trołłaskaje Lohkaje Cieła 1 (Nie apranajcie šałom z hetym pradmietam)"/>
  <string id="TrollocLight3" text="{.Nijaki}Trołłaskaje Lohkaje Cieła 3 (Nie apranajcie šałom z hetym pradmietam)"/>
  <string id="TrollocLight5" text="{.Nijaki}Trołłaskaje Lohkaje Cieła 5 (Nie apranajcie šałom z hetym pradmietam)"/>
  <string id="TrollocLight6" text="{.Nijaki}Trołłaskaje Lohkaje Cieła 6 (Nie apranajcie šałom z hetym pradmietam)"/>
  <string id="TrollocLight7" text="{.Nijaki}Trołłaskaje Lohkaje Cieła 7 (Nie apranajcie šałom z hetym pradmietam)"/>
  <string id="TrollocLight4" text="{.Nijaki}Trołłaskaje Lohkaje Cieła 4 (Nie apranajcie šałom z hetym pradmietam)"/>
  <string id="TrollocLight8" text="{.Nijaki}Trołłaskaje Lohkaje Cieła 8 (Nie apranajcie šałom z hetym pradmietam)"/>
  <string id="TrollocLight9" text="{.Nijaki}Trołłaskaje Lohkaje Cieła 9 (Nie apranajcie šałom z hetym pradmietam)"/>
  <string id="TrollocLight10" text="{.Nijaki}Trołłaskaje Lohkaje Cieła 10 (Nie apranajcie šałom z hetym pradmietam)"/>
  <string id="TrollocLight12" text="{.Nijaki}Trołłaskaje Lohkaje Cieła 12 (Nie apranajcie šałom z hetym pradmietam)"/>
  <string id="TrollocLight13" text="{.Nijaki}Trołłaskaje Lohkaje Cieła 13 (Nie apranajcie šałom z hetym pradmietam)"/>
  <string id="TrollocLight14" text="{.Nijaki}Trołłaskaje Lohkaje Cieła 14 (Nie apranajcie šałom z hetym pradmietam)"/>
  <string id="TrollocLight16" text="{.Nijaki}Trołłaskaje Lohkaje Cieła 16 (Nie apranajcie šałom z hetym pradmietam)"/>
  <string id="TrollocLight18" text="{.Nijaki}Trołłaskaje Lohkaje Cieła 18 (Nie apranajcie šałom z hetym pradmietam)"/>
  <string id="TrollocLight20" text="{.Nijaki}Trołłaskaje Lohkaje Cieła 20 (Nie apranajcie šałom z hetym pradmietam)"/>
  <string id="TrollocLight22" text="{.Nijaki}Trołłaskaje Lohkaje Cieła 22 (Nie apranajcie šałom z hetym pradmietam)"/>
  <string id="TrollocMED3" text="{.Muzcynski}Siaredni Trołłak 4 (Nie apranajcie šałom z hetym pradmietam)"/>
  <string id="TrollocMED2" text="{.Muzcynski}Siaredni Trołłak 5 (Nie apranajcie šałom z hetym pradmietam)"/>
  <string id="TrollocMED3b" text="{.Muzcynski}Siaredni Trołłak 6 (Nie apranajcie šałom z hetym pradmietam)"/>
  <string id="TrollocMED4" text="{.Muzcynski}Siaredni Trołłak 1 (Nie apranajcie šałom z hetym pradmietam)"/>
  <string id="TrollocMED5" text="{.Muzcynski}Siaredni Trołłak 2 (Nie apranajcie šałom z hetym pradmietam)"/>
  <string id="TrollocMED6" text="{.Muzcynski}Siaredni Trołłak 3 (Nie apranajcie šałom z hetym pradmietam)"/>
  <string id="TrollocHEV1" text="{.Muzcynski}Ciažki Trołłak 1 (Nie apranajcie šałom z hetym pradmietam)"/>
  <string id="TrollocHEV3" text="{.Muzcynski}Ciažki Trołłak 2 (Nie apranajcie šałom z hetym pradmietam)"/>
  <string id="TrollocHEV6" text="{.Muzcynski}Ciažki Trołłak 3 (Nie apranajcie šałom z hetym pradmietam)"/>
  <string id="TrollocHEV7" text="{.Muzcynski}Ciažki Trołłak 4 (Nie apranajcie šałom z hetym pradmietam)"/>
  <string id="TrollocHEV8" text="{.Muzcynski}Ciažki Trołłak 5 (Nie apranajcie šałom z hetym pradmietam)"/>
  <string id="TrollocHEV13" text="{.Muzcynski}Ciažki Trołłak 7 (Nie apranajcie šałom z hetym pradmietam)"/>
  <string id="TrollocHEV11" text="{.Muzcynski}Ciažki Trołłak-Pravadyr (Nie apranajcie šałom z hetym pradmietam)"/>
  <string id="gfQDDkEY" text="{.Muzcynski}Trołłaski Ščyt"/>
  <string id="tYVrECy7" text="{.Muzcynski}Trołłaski Ščyt"/>
  <string id="Aiel_shield" text="{.Muzcynski}Ajelski Bakler"/>
  <string id="offhandswordWOT" text="{.Muzcynski}Dapamožny Mieč NHP"/>
  <string id="offhandswordWOTweak" text="{.Muzcynski}Stary Dapamožny Mieč"/>
  <string id="AielWiseOneRobe1" text="{.Nijaki}Ajelskaje Adzieńnie Mudranicy"/>
  <string id="AielArmor1" text="{.Nijaki}Ajelskaje Adzieńnie Pany"/>
  <string id="AielArmor1b" text="{.Nijaki}Ajelskaje Miakkaje Adzieńnie Pany"/>
  <string id="AielArmor2" text="{.Nijaki}Ajelskaje Lohkaje Adzieńnie"/>
  <string id="AielArmor3" text="{.Nijaki}Ajelskaje Siaredniaje Adzieńnie"/>
  <string id="AielArmor4" text="{.Nijaki}Ajelskaje Miakkaje Adzieńnie"/>
  <string id="AielBoots1" text="{.Mnozny}Ajelskija Boty"/>
  <string id="AielHeadwrap1" text="{.Zanocy}Ajelskaja Čornaja Vual"/>
  <string id="Aielveilred" text="{.Zanocy}Ajelskaja Čyrvonaja Vual Sammy NSej"/>
  <string id="Aielbowlevel1" text="{.Muzcynski}Ajelski Doŭhi Łuk"/>
  <string id="Aielbowlevel2" text="{.Muzcynski}Ajelski Hruntoŭny Doŭhi Łuk"/>
  <string id="Aielarrows1" text="{.Mnozny}Ajelskija Streły"/>
  <string id="Aielarrows2" text="{.Mnozny}Ajelskija Hruntoŭnyja Streły"/>
  <string id="Asharmor1" text="{.Nijaki}Ašamanskaje Sałdackaje Adzieńnie "/>
  <string id="Asharmor2" text="{.Nijaki}Ašamanskaje Paśviačonaje Adzieńnie"/>
  <string id="Asharmor3" text="{.Nijaki}Ašamanskaje Adzieńnie z Cmačynaj Špilkaj"/>
  <string id="AshBoots1" text="{.Mnozny}Ašamanskija Boty"/>
  <string id="Asharmorgloves" text="{.Mnozny}Ašamanskija Skuranyja Naručy"/>
  <string id="WarderArmorMediumweak" text="{.Zanocy}Brania Nahladnika-Navika"/>
  <string id="WarderarmorLight" text="{.Zanocy}Lohkaja Brania Nahladnika"/>
  <string id="WarderArmorMedium" text="{.Zanocy}Siaredniaja Brania Nahladnika"/>
  <string id="WarderArmorMediumcheap" text="{.Zanocy}Tannaja Siaredniaja Brania Nahladnika"/>
  <string id="WarderArmorMedium2" text="{.Zanocy}Siaredniaja Brania Nahladnika"/>
  <string id="WarderHeavyArmor" text="{.Zanocy}Ciažkaja Brania Nahladnika"/>
  <string id="WarderCloak" text="{.Nijaki}Pokryva Nahladnika"/>
  <string id="WarderCloakcheap" text="{.Nijaki}Tannaje Pokryva Nahladnika"/>
  <string id="WarderBootsLight" text="{.Mnozny}Skuranyja Boty"/>
  <string id="WarderBootsLightCheap" text="{.Mnozny}Tannyja Skuranyja Boty"/>
  <string id="WarderHeavyBracer" text="{.Mnozny}Naručy Nahladnika"/>
  <string id="Warderheavyboots" text="{.Mnozny}Ciažkija Boty Nahladnika"/>
  <string id="WhiteTowerCloak" text="{.Nijaki}Biełavieskaje Pokryva"/>
  <string id="WhiteTowerLighttArmorcloth" text="{.Zanocy}Biełavieskaja Lohkaja Brania"/>
  <string id="WhiteTowerLighttArmor" text="{.Zanocy}Biełavieskaja Siaredniaja Brania"/>
  <string id="WhiteTowerHeavyArmor" text="{.Zanocy}Biełavieskaja Ciažkaja Brania"/>
  <string id="WhiteTowerLightHelm" text="{.Muzcynski}Biełavieski Lohki Šałom"/>
  <string id="WhiteTowerHeavyHelm" text="{.Muzcynski}Biełavieski Ciažki Šałom"/>
  <string id="WhiteTowerBoots" text="{.Mnozny}Biełavieskija Boty"/>
  <string id="WhiteTowerShield1" text="{.Muzcynski}Biełavieski Ščyt"/>
  <string id="Andornew2024helm1c" text="{.Muzcynski}Andorski Rekrucki Šałom Varty Karalevy"/>
  <string id="AndorQueensguardHelmet" text="{.Muzcynski}Andorski Stary Stylovy Šałom Varty Karalevy"/>
  <string id="AndorQueensguardHelmetold" text="{.Muzcynski}Andorski Stary Stylovy Šałom Varty Karalevy"/>
  <string id="AndorShoulders" text="{.Mnozny}Andorskija Plečavyja Płaściny"/>
  <string id="Andornew2024boots1b" text="{.Mnozny}Andorskija Boty Varty Karalevy"/>
  <string id="AndorQueenguardBootsHeavyold" text="{.Mnozny}Andorskija Staryja Stylovyja Boty Varty Karalevy"/>
  <string id="AndorQueenguardBootsHeavy" text="{.Mnozny}Andorskija Drenna Zroblenyja Boty Varty Karalevy"/>
  <string id="AndorQueenguardglovesHeavy" text="{.Mnozny}Andorskija Naručy Varty Karalevy"/>
  <string id="AndorQueenguardglovesHeavyold" text="{.Mnozny}Andorskija Staryja Stylovyja Naručy Varty Karalevy"/>
  <string id="AndorQueenguardheavy" text="{.Zanocy}Andorskaja Brania Varty Karalevy"/>
  <string id="AndorQueenguardheavynew" text="{.Zanocy}Andorskaja Rycarskaja Brania"/>
  <string id="AndorQueenguardheavy2" text="{.Zanocy}Andorskaja Brania Varty Karalevy"/>
  <string id="AndorQueenguardheavyold" text="{.Zanocy}Staraja Stylovaja Andorskaja Brania Varty Karalevy"/>
  <string id="andorRoyalarmorhelm" text="{.Muzcynski}Andorski Karaleŭski Šałom"/>
  <string id="andorRoyalarmorboots1" text="{.Mnozny}Andorskija Karaleŭskija Boty"/>
  <string id="andorRoyalarmorgloves1" text="{.Mnozny}Karaleŭskija Naručy"/>
  <string id="andorRoyalarmorplate2" text="{.Zanocy}Andorskaja Karaleŭskaja Brania"/>
  <string id="andorRoyalarmorplate1" text="{.Zanocy}Andorskaja Hienieralskaja Karaleŭskaja Brania"/>
  <string id="AndorShield1" text="{.Muzcynski}Andorski Mietaličny Ščyt"/>
  <string id="AndorCommonArmorHeavy2" text="{.Zanocy}Andorskaja Prostaja Ciažkaja Brania z Łancuhovaj Kalčuhaj"/>
  <string id="AndorCommonArmorHeavy3" text="{.Zanocy}Andorskaja Prostaja Ciažkaja Brania"/>
  <string id="AndorCommonArmorLight1" text="{.Zanocy}Andorskaja Prostaja Lohkaja Brania"/>
  <string id="AndorCommonArmorLight2" text="{.Zanocy}Andorskaja Prostaja Lohkaja Brania z Łancuhovaj Kalčuhaj"/>
  <string id="AndorNobleArmor1" text="{.Zanocy}Andorskaja Šlachietnaja Brania"/>
  <string id="AndorNobleArmor2" text="{.Zanocy}Andorskaja Šlachietnaja Brania sa Skuranymi Rukavami"/>
  <string id="AndorNobleArmor3" text="{.Zanocy}Tannaja Andorskaja Płaścinavaja Brania Varty Karalevy"/>
  <string id="andorqueenguard2024kn1" text="{.Zanocy}Andorskaja Rycarskaja Brania"/>
  <string id="andorknight2024lighred" text="{.Zanocy}Andorskaja Rycarskaja Lohkaja Brania"/>
  <string id="andorknight2024light1" text="{.Zanocy}Andorskaja Rycarskaja Lohkaja Brania"/>
  <string id="andorknight2024light1b" text="{.Zanocy}Andorskaja Rycarskaja Lohkaja Brania"/>
  <string id="andorknight2024recuit1" text="{.Zanocy}Andorskaja Rycarskaja Lohkaja Brania"/>
  <string id="andorknight2024recuit1b" text="{.Zanocy}Andorskaja Rycarskaja Lohkaja Brania"/>
  <string id="AndorNobleArmor3old" text="{.Zanocy}Andorskaja Staraja Stylovaja Šlachietnaja Ciažkaja Brania"/>
  <string id="AndorNobleArmor4" text="{.Zanocy}Andorskaja Šlachietnaja Ciažkaja Brania"/>
  <string id="AndorNobleBoots1old" text="{.Mnozny}Andorskija Šlachietnyja Boty"/>
  <string id="AndorNobleBoots1" text="{.Mnozny}Andorskija Šlachietnyja Boty"/>
  <string id="AndorCommonBoots1" text="{.Mnozny}Andorskija Prostyja Boty"/>
  <string id="AndorCommonBracers" text="{.Mnozny}Andorskija Naručy"/>
  <string id="AndorCommonHelm1" text="{.Muzcynski}Andorski Prosty Šałom"/>
  <string id="AndorNobleHelm1" text="{.Muzcynski}Andorski Šlachietny Šałom"/>
  <string id="TEARShield1" text="{.Muzcynski}Cirski Ciažki Ščyt"/>
  <string id="TEARShield3" text="{.Muzcynski}Cirski Lohki Ščyt"/>
  <string id="TearDefenderHelm1" text="{.Muzcynski}Cirski Lohki Šałom Abaronca Kamiania"/>
  <string id="TearDefenderHelm2" text="{.Muzcynski}Cirski Ciažki Šałom Abaronca Kamiania"/>
  <string id="TearDefenderBoots" text="{.Mnozny}Załatyja Płaścinkavyja Boty"/>
  <string id="TearDefenderHands" text="{.Mnozny}Cirskija Naručy Abaronca Kamiania"/>
  <string id="TearDefenderArmor1" text="{.Zanocy}Cirskaja Brania Abaronca Kamiania"/>
  <string id="TearNobleHelmHeavy" text="{.Muzcynski}Cirski Šlachietny Ciažki Rycarski Šałom"/>
  <string id="TearNobleHelmHeavy2" text="{.Muzcynski}Cirski Šlachietny Lohki Rycarski Šałom"/>
  <string id="TearNobleHelmLight1" text="{.Muzcynski}Cirski Šlachietny Lohki Šałom"/>
  <string id="TearNobleHelmLight2" text="{.Muzcynski}Cirski Šlachietny Ciažki Šałom"/>
  <string id="TearNoblebootsHeavy" text="{.Mnozny}Cirskija Ciažkija Boty"/>
  <string id="TearNobleHeavy1" text="{.Zanocy}Cirskaja Ciažkaja Šlachietnaja Brania"/>
  <string id="TearNobleHeavy3" text="{.Zanocy}Cirskaja Prostaja Ciažkaja Brania"/>
  <string id="TearNobleLight1" text="{.Zanocy}Cirskaja Šlachietnaja Lohkaja Brania"/>
  <string id="TearNoblelight3" text="{.Zanocy}Cirskaja Prostaja Lohkaja Brania"/>
  <string id="GhealdanLegionHelm1" text="{.Muzcynski}Hiealdanski Šałom Lehijona Ściany"/>
  <string id="GhealdanLegionHelm2" text="{.Muzcynski}Hiealdanski Šałom Lehijona Ściany"/>
  <string id="GhealdanLegionLightArmor" text="{.Zanocy}Hiealdanskaja Lohkaja Brania Lehijona Ściany"/>
  <string id="GhealdanLegionMediumArmor" text="{.Zanocy}Hiealdanskaja Siaredniaja Brania Lehijona Ściany"/>
  <string id="Ghealdenheavy2024newarmor1b" text="{.Zanocy}Hiealdanskaja Łancuhovaja Kalčuha Lehijona Ściany"/>
  <string id="Ghealdenheavy2024newarmor1" text="{.Zanocy}Hiealdanskaja Płaścinkavaja Kalčuha Lehijona Ściany"/>
  <string id="Ghealden2024boots1" text="{.Mnozny}Hiealdanskija Skuranyja Boty"/>
  <string id="Ghealdenheavy2024newshoulder1" text="{.Mnozny}Hiealdanskija Płaścinkavyja Naplečniki"/>
  <string id="Hornofvalere1" text="{.Muzcynski}Roh Valera"/>
  <string id="onepowerblossomsoffiresingle" text="{.Zanocy}Adzinaja Moc: Adna Vohnienaja Strała Navika (Blizkaja Dystancyja)"/>
  <string id="onepowerflamingarrowingle" text="{.Zanocy}Adzinaja Moc: Adna Vohnienaja Strała (Blizkaja Dystancyja)"/>
  <string id="onepowerflamingarrowingleMULTI" text="{.Zanocy}Adzinaja Moc: Šmat Vohniennych Strełaŭ (Mnostva Snaradaŭ)(Blizkaja Dystancyja)"/>
  <string id="onepowerblossomsoffiretrue" text="{.Zanocy}Adzinaja Moc: Adna Vohniennaja Kvietka (Blizkaja Dystancyja)"/>
  <string id="onepowerblossomsoffire" text="{.Zanocy}Adzinaja Moc: Niekalki Vohniennych Kvietak (Blizkaja Dystancyja)"/>
  <string id="Onepowerfireball1" text="{.Zanocy}Adzinaja Moc: Vohnienny Šar (Blizkaja Dystancyja)"/>
  <string id="onepowerwindstorm1FireBall" text="{.Zanocy}Adzinaja Moc: Słaby Dalokabojny Vohnienny Šar (Patrabuje Zarady)"/>
  <string id="onepowerwindstorm1FireBall2" text="{.Zanocy}Adzinaja Moc: Mocny Dalokabojny Vohnienny Šar (Patrabuje Zarady)"/>
  <string id="onepowerwindstorm1FireBall3" text="{.Zanocy}Adzinaja Moc: Vielmi Mocny Dalokabojny Vohnienny Šar (Patrabuje Zarady)"/>
  <string id="onepowerwindstorm1Fireballammoarrow" text="{.Zanocy}Adzinaja Moc: Zarady Vohniennaj Strały (Vykarystoŭvać z Adzinaj Mocaj Dalokaj Dystancyi)"/>
  <string id="onepowerwindstorm1Fireballammo" text="{.Zanocy}Adzinaja Moc: Zarady Vohniennaha Šaru (Vykarystoŭvać z Adzinaj Mocaj Dalokaj Dystancyi)"/>
  <string id="onepowerwindstorm1Lightningammo" text="{.Zanocy}Adzinaja Moc: Zarady Maleńkaha Małankavaha Štormu (Vykarystoŭvać z Adzinaj Mocaj Dalokaj Dystancyi)"/>
  <string id="onepowerwindstorm1LightningammoLarger" text="{.Zanocy}Adzinaja Moc: Zarady Vialikaha Małankavaha Štormu (Vykarystoŭvać z Adzinaj Mocaj Dalokaj Dystancyi)"/>
  <string id="onepowerwindstorm1Blossomammo" text="{.Zanocy}Adzinaja Moc: Zarady Kvitnieńnia Ahniu (Vykarystoŭvać z Adzinaj Mocaj Dalokaj Dystancyi)"/>
  <string id="onepowerwindstormearthammo" text="{.Zanocy}Adzinaja Moc: Zarady Zaviruchi Ziamli i Ahniu (Vykarystoŭvać z Adzinaj Mocaj Dalokaj Dystancyi)"/>
  <string id="onepowerwindsbalefireammo" text="{.Zanocy}Adzinaja Moc: Zarady Maleńkaha Vohniennaha Stosu (Vykarystoŭvać z Adzinaj Mocaj Dalokaj Dystancyi)"/>
  <string id="onepowerwindsbalefireammolarger" text="{.Zanocy}Adzinaja Moc: Zarady Vialikaha Vohniennaha Stosu (Vykarystoŭvać z Adzinaj Mocaj Dalokaj Dystancyi)"/>
  <string id="onepowerrollingearthandfire" text="{.Zanocy}Adzinaja Moc: Zavirucha Ziamli i Ahniu (Adna)(Blizkaja Dystancyja) "/>
  <string id="onepowerrollingearthandfireMULT" text="{.Zanocy}Adzinaja Moc: Zavirucha Ziamli i Ahniu (Mnostva Snaradaŭ)(Blizkaja Dystancyja)"/>
  <string id="onepowerbalefiresmall" text="{.Zanocy}Adzinaja Moc: Maleńki Vohnienny Stos (Blizkaja Dystancyja)"/>
  <string id="onepowerbalefire" text="{.Zanocy}Adzinaja Moc: Vialiki Vohnienny Stos (Blizkaja Dystancyja)"/>
  <string id="OnePowerAirShield" text="{.Zanocy}Adzinaja Moc: Maleńki Pavietrany Ščyt"/>
  <string id="OnePowerAirShieldLarger" text="{.Zanocy}Adzinaja Moc: Vialiki Pavietrany Ščyt"/>
  <string id="OnePowerAirShieldMega" text="{.Zanocy}Adzinaja Moc: Mieha Pavietrany Ščyt"/>
  <string id="onepowerlightningstormsmall" text="{.Zanocy}Adzinaja Moc: Maleńkaja Małanka (Blizkaja Dystancyja)"/>
  <string id="onepowerlightningstormlarger" text="{.Zanocy}Adzinaja Moc: Vialikaja Małanka (Blizkaja Dystancyja)"/>
  <string id="onepowerwindstorm1" text="{.Zanocy}Adzinaja Moc: Vietrany Štorm (Patrabuje Zarady Vietranaha Štormu)"/>
  <string id="onepowerwindstor2weak1" text="{.Zanocy}Adzinaja Moc: Słaby Vietrany Štorm (Patrabuje Zarady Vietranaha Štormu)"/>
  <string id="onepowerwindstorm1ammo" text="Zarady Vietranaha Štormu (Patrabujuć Vietrany Štorm)"/>
  <string id="Onepowerwindblast" text="{.Zanocy}Adzinaja Moc: Vietrany Vybuch (Mnostva Snaradaŭ)(Blizkaja Dystancyja)"/>
  <string id="OnepowerwindblastNPC" text="{.Zanocy}Adzinaja Moc: Vietrany Vybuch (Adzin)(Blizkaja Dystancyja)"/>
  <string id="RandAlthorOutfit" text="{.Nijaki}Ubrańnie Cmačynaha Pieraradžeńnia"/>
  <string id="MatCauthonOutfit" text="{.Nijaki}Ubrańnie Mata"/>
  <string id="MatCuthonFoxheadmeddalion" text="{.Muzcynski}Miedaljon Lisinaja Hałava"/>
  <string id="MatCuthonHat" text="{.Muzcynski}Kapialuch Mata"/>
  <string id="Whitecloakcloak1" text="{.Nijaki}Pokryva Biełych Pokryvaŭ"/>
  <string id="WhitecloakBoots1" text="{.Mnozny}Boty Biełych Pokryvaŭ"/>
  <string id="WhitecloakLightarmor1" text="{.Zanocy}Lohkaja Brania Biełych Pokryvaŭ"/>
  <string id="WhitecloakLightarmor2" text="{.Zanocy}Lohkaja Brania Biełych Pokryvaŭ"/>
  <string id="WhitecloakMediumArmor1" text="{.Zanocy}Siaredniaja Brania Biełych Pokryvaŭ"/>
  <string id="WhitecloakMediumArmor2" text="{.Zanocy}Siaredniaja Brania Biełych Pokryvaŭ"/>
  <string id="WhitecloakMediumArmor2b" text="{.Zanocy}Siaredniaja Brania Biełych Pokryvaŭ"/>
  <string id="WhitecloakHeavyArmor1" text="{.Zanocy}Ciažkaja Brania Biełych Pokryvaŭ"/>
  <string id="WhitecloakLightHelmet" text="{.Muzcynski}Lohki Šałom Biełych Pokryvaŭ"/>
  <string id="WhitecloakHeavyHelmet" text="{.Muzcynski}Ciažki Šałom Biełych Pokryvaŭ"/>
  <string id="Redbandhelm" text="Čyrvony Band Šałom"/>
  <string id="Perrinarmor" text="Perrins Ubrańnie"/>
  <string id="Perrinboots" text="Perrins Boty"/>
  <string id="AesSedaiAcceptedRobe" text="Aes Sedai Accepted Robe"/>
  <string id="AesSedaiNoviceRobe" text="Aes Sedai Navika Robe"/>
  <string id="AessedaiGreen" text="Aes Sedai Green Robe"/>
  <string id="AessedaiBlue" text="Aes Sedai Blue Robe"/>
  <string id="AessedaiBlack" text="Čorny Robe"/>
  <string id="AessedaiBrown" text="Aes Sedai Brown Robe"/>
  <string id="AessedaiGrey" text="Aes Sedai Grey Robe"/>
  <string id="AessedaiRed" text="Aes Sedai Čyrvony Robe"/>
  <string id="AessedaiWhite" text="Aes Sedai White Robe"/>
  <string id="AessedaiYellow" text="Aes Sedai Yellow Robe"/>
  <string id="Aessedaishoes" text="Simple Shoes"/>
  <string id="TwoRivers_ArcherHood" text="Two Rivers Archer Hood"/>
  <string id="TwoRiversBoots2" text="Skurany Boty"/>
  <string id="TwoRiversBoots1" text="Two Rivers Boty"/>
  <string id="TwoRiversHeavyArmor1" text="Two Rivers Ciažkaja Brania"/>
  <string id="TwoRiversHeavyArmor2" text="Two Rivers Ciažkaja Brania"/>
  <string id="TwoRiversMediumarmor1" text="Two Rivers Siaredniaja Brania"/>
  <string id="TwoRiversArcher2" text="Two Rivers Siaredniaja Brania"/>
  <string id="TwoRiversArcher1" text="Two Rivers Archer Brania"/>
  <string id="TwoRivers_Farmer2" text="Two Rivers Farmer Ubrańnie"/>
  <string id="TwoRivers_Farmer1" text="Two Rivers Farmer Ubrańnie"/>
  <string id="Tworiversbow1" text="Two Rivers Łuk"/>
  <string id="Tworiversbow2" text="Two Rivers Hunting Łuk"/>
  <string id="tworiversarrows2" text="Two Rivers Streły"/>
  <string id="IllianerShoulders" text="Illianer Płaścinkavyja Naplečniki"/>
  <string id="IllianerCompanionHelmet1old" text="Illianer Stary Stylovy Šałom"/>
  <string id="Illianset2mischelm1" text="Illianer Companion Plate Šałom"/>
  <string id="Illianset2mischelm2" text="Illianer Plate Šałom"/>
  <string id="Illianset2mischelm3" text="Illianer Plate Šałom"/>
  <string id="IllianerCompanionHelmet1" text="Illianer Low Quality Šałom"/>
  <string id="IllianerCompanionHelmet2" text="Illianer Ciažki Šałom"/>
  <string id="IllianerHeavyBoots" text="Illianer Ciažki Boty"/>
  <string id="IllianerGloves" text="Illianer Naručy"/>
  <string id="IllianerCompanionHeavyArmor1misc" text="Illianer Ciažkaja Brania"/>
  <string id="IllianerCompanionHeavyArmor1Cheapmisc" text="Dented Illianer Ciažkaja Brania "/>
  <string id="IllianerCompanionHeavyArmor1Startmisc" text="Illianer Low Quality Ciažkaja Brania "/>
  <string id="IllianerCompanionHeavyArmor2misc" text="Illianer Ciažkaja Brania"/>
  <string id="IllianerIllCompaionarmorFullmisc" text="Illianer Ciažkaja Brania z Łancuhovaj Kalčuhaj"/>
  <string id="IllianerCompanionHeavyArmor1" text="Illianer Companion Ciažkaja Brania "/>
  <string id="IllianerCompanionHeavyArmor2" text="Illianer Companion Ciažkaja Brania"/>
  <string id="Illianerharnessbase" text="Basic Illianer Companion Harness"/>
  <string id="IllianerIllCompaionarmorFull" text="Illianer Companion Ciažkaja Brania z Łancuhovaj Kalčuhaj"/>
  <string id="IllianerIllCompaionarmorFullLegend" text="Illianer Companion Legend Brania"/>
  <string id="illiacompanionshoulderroyal" text=" Royal Płaścinkavyja Naplečniki"/>
  <string id="Illiancompaniongloveroyal1" text="Royal Illianer Naručy"/>
  <string id="IllianerNolbeHelm1" text="Illianer Šlachietny Šałom"/>
  <string id="CairhienNobleHelm1" text="Cairhien Šlachietny Šałom"/>
  <string id="CairhienNobleHelm2" text="Cairhien Šlachietny Sergeant Šałom"/>
  <string id="CairhienNobleHelm3" text="Cairhien Šlachietny Officer Šałom"/>
  <string id="CairhienHouseHeavyCommon3" text="Cairhien Šlachietny Ciažkaja Brania"/>
  <string id="CairhienHouseLight1" text="Cairhien Šlachietny Lohkaja Brania"/>
  <string id="carabenarmorlight1b" text="Cairhien Łancuhova-Kalčužny Shirt"/>
  <string id="carabenarmormeidiem1" text="Cairhien Chestplate z Mail"/>
  <string id="carabenarmormeidiem1b" text="Cairhien Chestplate z Adzieńniem"/>
  <string id="CairhienGloves1" text="Ciažki Plate Naručy z leather Naručy"/>
  <string id="CairhienHouseHeavyBoots" text="Cairhien Boty"/>
  <string id="KandorHeavyBoots1" text="Kandor Ciažki Boty"/>
  <string id="wotset6miscarmor1" text="Miakki Gamberson"/>
  <string id="wotset6miscarmor1c" text="Miakki Gamberson With Skurany"/>
  <string id="wotset6miscarmor1e" text="Miakki Gamberson With Skurany"/>
  <string id="wotset6miscarmor1b" text="Miakki Gamberson z Łancuhovaja Kalčuhaj"/>
  <string id="wotset6miscarmor1f" text="Ciažki Miakki Gamberson With Mail"/>
  <string id="wotset6miscarmor1d" text="Ciažki Miakki Gamberson and Mail"/>
  <string id="KandorLightArmor" text="Kandor Lohkaja Brania"/>
  <string id="KandorMediumArmor" text="Kandor Siaredniaja Brania"/>
  <string id="KandorHeavyArmor" text="Kandor Ciažkaja Brania"/>
  <string id="KandorHelm1" text="Kandor Łancuhova-Kalčužny Helm"/>
  <string id="SaldeaBoots1" text="Saldea Boty"/>
  <string id="SaldeaHeavyArmor2" text="Saldea Ciažkaja Brania z Łancuhovaj Kalčuhaj"/>
  <string id="SaldeaHeavyArmor2cheap" text="Saldea Tanny Brania z Łancuhovaj Kalčuhaj"/>
  <string id="SaldeaHeavyArmor1" text="Saldea Ciažkaja Brania"/>
  <string id="SaldeaCavalryarmor1" text="Saldea Lohki Cavalry armor"/>
  <string id="SaldeaMediumCavalryarmor" text="Saldea Siaredni Cavalry armor"/>
  <string id="SaldeaCavalryarmor2" text="Saldea Lohki Cavalry Brania z Łancuhovaja Kalčuhaj"/>
  <string id="SaldeaLightarmor3" text="Saldea Lohkaja Brania"/>
  <string id="SaldeaLightarmor4" text="Saldea Lohkaja Brania"/>
  <string id="SaldeaLightarmor2" text="Saldea Lohkaja Brania z Łancuhovaja Kalčuhaj"/>
  <string id="SaldeaLightarmor1" text="Saldea Lohkaja Brania"/>
  <string id="SaldeaHeavyHelmet2" text="Saldea Ciažki Šałom"/>
  <string id="SaldeaHeavyHelmet1" text="Saldea Ciažki Šałom"/>
  <string id="SaldeaMediumHelmet1" text="Saldea Siaredni Šałom"/>
  <string id="SaldeaLightHelmet1" text="Saldea Lohki Šałom"/>
  <string id="SaldeaShield1" text="Saldea Ščyt"/>
  <string id="WotDreadlordLightarmor" text="Dreadlord Lohkaja Brania"/>
  <string id="WotDreadlordMedarmor" text="Dreadlord Ciažkaja Brania"/>
  <string id="ArafelLightHelmet" text="Arafel Lohki Šałom"/>
  <string id="ArafelMediumHelmet" text="Arafel Šałom"/>
  <string id="ArafelMediumHelmet2" text="Arafel Siaredni Šałom"/>
  <string id="ArafelHeavyHelmet1" text="Arafel Ciažki Šałom"/>
  <string id="ArafelBoots1" text="Arafel Boty"/>
  <string id="ArafelGloves1" text="Arafel Patched Steel Naručy"/>
  <string id="wotset6miscarmor2" text="Studded Skurany Ubrańnie"/>
  <string id="wotset6miscarmor2b" text="Studded Skurany Jacket z Skurany Arms"/>
  <string id="wotset6miscarmor2c" text="Studded Skurany Jacket z Skurany Arms"/>
  <string id="ArafelLightArmor1" text="Arafel Lohkaja Brania"/>
  <string id="ArafelLightArmor2" text="Arafel Lohkaja Brania z Plates"/>
  <string id="ArafellMediumArmor1" text="Arafel Siaredniaja Brania z Łancuhovaja Kalčuhaj"/>
  <string id="ArafelMediumArmor2" text="Arafel Siaredniaja Brania"/>
  <string id="W9bsRAfD" text="Arafel Shoulder Guards"/>
  <string id="DragonLegionLight" text="Legion of The Dragon Lohkaja Brania"/>
  <string id="DragonLegionHeavy" text="Legion of The Dragon Ciažkaja Brania"/>
  <string id="FarmaddingLightArmor" text="Far Madding Lohkaja Brania"/>
  <string id="FarmaddingHeavyArmor" text="Far Madding Ciažkaja Brania"/>
  <string id="Farmaddinghelm1" text="Far Madding Guard Šałom"/>
  <string id="Shienerhelm1" text="Levy Šałom z Łancuhovaj Kalčuhaj"/>
  <string id="Shienerhelm2" text="Arad Doman Levy Šałom"/>
  <string id="WOTlevyarmor1" text="Levy Płaścinavaja Brania z Łancuhovaja Kalčuhaj"/>
  <string id="WOTlevyarmor2" text="Levy Fur and Skurany Brania"/>
  <string id="WOTlevyarmor3" text="Levy Lohki Skurany Coat z Łancuhovaj Kalčuhaj "/>
  <string id="WOTlevyarmor3med" text="Levy Siaredni Miakki Coat z Łancuhovaj Kalčuhaj"/>
  <string id="WOTlevyarmor3hev" text="Levy Ciažki Miakki Coat z Łancuhovaj Kalčuhaj"/>
  <string id="WOTlevyarmor4" text="Levy Tanny Skurany and Rags"/>
  <string id="WOTlevyarmor4b" text="Levy Tanny Skurany and Rags z Łancuhovaj Kalčuhaj"/>
  <string id="WOTlevyarmor4c" text="Levy Tanny Skurany and Rags z Plates"/>
  <string id="WOTlevyarmor4d" text="Levy Average Quality Skurany z Łancuhovaj Kalčuhaj"/>
  <string id="WOTlevyarmor4e" text="Levy Average Quality Skurany z Łancuhovaj Kalčuhaj"/>
  <string id="WOTlevyarmor4f" text="Levy Tanny Skurany z Łancuhovaj Kalčuhaj Coat"/>
  <string id="WOTlevyarmor4g" text="Levy Tanny Skurany z Rags and Łancuhova-Kalčužny Coat"/>
  <string id="WOTlevyarmor5" text="Levy Brania (NPC only)"/>
  <string id="WOTlevyarmor5b" text="Levy Brania (NPC only)"/>
  <string id="WOTlevyarmor6" text="Levy Good Quality Skurany z Łancuhovaj Kalčuhaj"/>
  <string id="WOTlevyarmor7" text="Levy Average Quality Skurany Coat z Łancuhovaj Kalčuhaj"/>
  <string id="WOTlevyarmor8" text="Levy Brestplate z Adzieńniem"/>
  <string id="WOTlevyarmor8b" text="Levy Brestplate Adzieńnie z Łancuhovaj Kalčuhaj"/>
  <string id="WOTlevyarmor9" text="Levy Tanny Adzieńnie"/>
  <string id="WOTlevyarmor9b" text="Levy Tanny Adzieńnie z Łancuhovaj Kalčuhaj"/>
  <string id="WOTlevyarmor9c" text="Levy Tanny Quality Plates"/>
  <string id="WOTlevyarmor9d" text="Levy Tanny Quality Plates z Łancuhovaj Kalčuhaj"/>
  <string id="WOTlevyarmor9Hev" text="Levy Good Quality Płaścinavaja Brania z Łancuhovaj Kalčuhaj"/>
  <string id="WOTlevyarmor9med" text="Levy Average Quality Płaścinavaja Brania z Łancuhovaj Kalčuhaj"/>
  <string id="WOTlevyarmor9medb" text="Levy Average Quality Płaścinavaja Brania z Łancuhovaj Kalčuhaj"/>
  <string id="WOTlevyarmor10" text="Levy Average Quality Cloth Brania"/>
  <string id="WOTlevyarmor10b" text="Levy Average Quality Cloth Brania z Łancuhovaja Kalčuhaj"/>
  <string id="MayeneWingedGuardHelmet" text="Mayene Winged Guard Šałom"/>
  <string id="MayeneWingedGuardHelmetLitenet" text="Mayene Winged Guard Lieutenant Šałom"/>
  <string id="MayeneWingedGuardHelmetCapt" text="Mayene Winged Guard Captain Šałom"/>
  <string id="MayeneWingedGuardboots" text="Mayene Winged Guard Boty"/>
  <string id="MayeneWingedGuardGloves" text="Mayene Winged Guard Naručy"/>
  <string id="MayeneWingedGuardArmor1" text="Mayene Winged Guard Brania"/>
  <string id="ShienarLighthelmetold" text="Stary Stylovy Shienar Lohki Šałom"/>
  <string id="shine2024newhelm2" text="Stary Shienar Lohki Šałom"/>
  <string id="ShienarLighthelmet" text="Shienar Lohki Šałom"/>
  <string id="ShienarLighthelmetcheap2" text="Tanny Shienar Lohki Šałom"/>
  <string id="shine2024newhelmroyal2" text="Shienar Royal Šałom"/>
  <string id="ShienarHeavyHelmet" text="Shienar Ciažki Šałom"/>
  <string id="ShienerLightBoots" text="Shiener Boty"/>
  <string id="Shiener2024newboots1cheap" text="Tanny Shiener Płaścinkavyja Boty"/>
  <string id="Shiener2024newboots1" text="Shiener Płaścinkavyja Boty"/>
  <string id="ShienerLightArmor1" text="Shiener Lohkaja Brania Blue"/>
  <string id="Shiner2024meidemarmor3" text="Shiener Lohkaja Brania Brown"/>
  <string id="ShienerMediumArmor2" text="Shienar Miakki Siaredniaja Brania"/>
  <string id="Shiner2024meidemarmor4" text="Shienar Łancuhova-Kalčužny Siaredniaja Brania"/>
  <string id="Shiner2024meidemarmor5" text="Shienar Łancuhova-Kalčužny Siaredniaja Brania"/>
  <string id="ShienerHeavyArmor2" text="Shiener Lohki Płaścinavaja Brania"/>
  <string id="ShienerHeavyArmor3" text="Shiener Siaredni Płaścinavaja Brania"/>
  <string id="ShienerHeavyArmor3cheap" text="Tanny Shiener Siaredni Płaścinavaja Brania"/>
  <string id="ShienarFullplateArmor" text="Shienar Ciažki Płaścinavaja Brania"/>
  <string id="ShienerHeavyShoulders" text="Shiener Shoulder Plates"/>
  <string id="Shiener2024newshoulders2" text=" Royal Shoulder Plates"/>
  <string id="Shiener2024royalarmor1" text="Shienar Royal Emblem Brania"/>
  <string id="Shiener2024royalarmor2" text="Shienar Plain Royal Brania"/>
  <string id="Shiener2024royalboots1" text="Shiener Royal Płaścinkavyja Boty"/>
  <string id="TarabonKingslifeguardarmor1" text="Tarabon Kings Life Guard Brania"/>
  <string id="TarabonPanarchslegion" text="Tarabon Panarchs Legion Brania"/>
  <string id="Redbandarmor1" text="Band of the Čyrvony Hand Lohkaja Brania"/>
  <string id="Redbandarmor1med" text="Band of the Čyrvony Hand Siaredniaja Brania"/>
  <string id="gA8mOXrC" text="Band of the Čyrvony Hand Plate Pauldrons"/>
  <string id="Redbandarmor11hev" text="Band of the Čyrvony Hand Ciažkaja Brania"/>
  <string id="SeanchanarmorLight" text="Seanchan Lohkaja Brania"/>
  <string id="Seanchanarmorheavy" text="Seanchan Ciažkaja Brania"/>
  <string id="Seanchanglovesa" text="Seanchan Naručy"/>
  <string id="SeanchanShield1" text="Seanchan Ščyt"/>
  <string id="SeanchanShield1Death" text="Seanchan Deathwatch Ščyt"/>
  <string id="Seanchanhelm2Claws" text="Seanchan Lohki Šałom"/>
  <string id="Seanchanhelm1tusk" text="Seanchan Masked Lohki Šałom"/>
  <string id="Seanchan2024shouldersheavy1" text="Seanchan Shoulders"/>
  <string id="Seanchan2024headlight3" text="Seanchan Masked Lohki Horned Šałom"/>
  <string id="Seanchan2024headhev2" text="Seanchan Ciažki Horned Šałom"/>
  <string id="Seanchan2024headhev3" text="Seanchan Ciažki Antenna Šałom"/>
  <string id="Seanchanhelmdeathguardheavy" text="Seanchan Deathwatch Guard Claw Šałom"/>
  <string id="Seanchandeath2024helm2" text="Seanchan Deathwatch Guard Horned Šałom"/>
  <string id="Seanchandeathwatchguardarmorgloves" text=" Seanchan Deathwatch Naručy"/>
  <string id="Seanchandeathwatchguardarmorboots" text="Seanchan Deathwatch Boty"/>
  <string id="Seanchandeathwatchguardarmor" text="Seanchan Deathwatch Brania"/>
  <string id="Seanchan2024Deatharmor1" text="Seanchan Ciažki Deathwatch Brania"/>
  <string id="QwiI8Uho" text="AAA TEST WOTmountestonly"/>
  <string id="Malkier2024helmet" text="Malkier Šałom"/>
  <string id="Malkier2024helmetused" text="Stary Used Malkier Šałom"/>
  <string id="Malkier2024shoulders" text="Malkier Shoulders"/>
  <string id="Malkiergloves" text="Čorny Skurany Malkier Naručy"/>
  <string id="Malkierboots" text="Malkier Boty"/>
  <string id="MalkierarmorLight" text="Malkier Lohkaja Brania"/>
  <string id="Malkierarmor" text="Malkier Ciažkaja Brania"/>
  <string id="ILLUMpotbase" text="Illuminator Grenade"/>
  <string id="ILLUMsparklet1" text="Illuminator Sparkler"/>
  <string id="ILLUMsparklet1ammosparkler" text="Illuminator Sparkler Ammo"/>
  <string id="ILLUMsparklet1ammosparklerheavy" text="Illuminator Rocket Ammo"/>
  <string id="kindress1" text="Kinswomen Dress"/>
  <string id="kindress2" text="Šlachietny Kinswomen Dress"/>
  <string id="Myrddraalblade1" text="Myrddraal Power Wrought Two Handed Mieč"/>
  <string id="AielSpeargrade1" text="Ajelski Simple Short Spear"/>
  <string id="AielSpeargrade2" text="Ajelski Hruntoŭny Short Spear"/>
  <string id="AielSpeargrade3" text="Ajelski Warriors Short Spear"/>
  <string id="Trollocweapon1" text=" Trołłaski Mieč One Handed"/>
  <string id="Trollocweapon2" text="Trołłaski Mace One Handed"/>
  <string id="Trollocweapon3" text=" Trołłaski Club One Handed"/>
  <string id="Trollocweapon4" text="Trołłaski Axe One Handed"/>
  <string id="Trollocweapon5" text="Trołłaski Two Handed Axe"/>
  <string id="Trollocweapon6" text=" Trołłaski Two Handed Cleaver"/>
  <string id="CallandorWeapon" text="Callandor"/>
  <string id="Matspearweapon" text=" Mats Ashandarei"/>
  <string id="Wothalberd1" text="Mayene Halberd"/>
  <string id="Perrinsaxe" text="Perrins Axe"/>
  <string id="Fadevampiregauntlets1" text="Źniknieńnia Naručy"/>
  <string id="Fadevampirebboots1" text="Źniknieńnia Boty"/>
  <string id="Forsakenfemalerobes2" text="Forsaken Female Adzieńnie"/>
  <string id="Forsakenmale1" text="Forsaken Male Adzieńnie"/>
  <string id="illiacompanionshouldersset1type1" text="Illianer Companion Shoulders"/>
  <string id="Illianset2bootstype1" text="Illian Companion Ciažki Boty"/>
  <string id="Illiancompanionbootsset2type2" text="Illian Ciažki Boty"/>
  <string id="Illiancompanionglovesset2type1" text="Illian Companion Naručy"/>
  <string id="Illiancompanionglovesset2type1cheap" text="Tanny Illian Companion Naručy"/>
  <string id="Illianhelmset2type1" text="Illianer Companion Šałom"/>
  <string id="Illianset2bootroyal1" text="Illian Royal Płaścinkavyja Boty"/>
  <string id="Pany2024armorplatecloth" text="Pany of the Mieč Lohkaja Brania"/>
  <string id="Pany2024armorplatechainmail" text="Pany of the Mieč Lohki Plate Łancuhova-Kalčužny"/>
  <string id="Pany2024armorlightplate2" text="Pany of the Mieč Robe Plate"/>
  <string id="Pany2024armorlightplate2b" text="Pany of the Mieč Skurany Studded Robe Plate"/>
  <string id="Pany2024armorlightplate1" text="Pany of the Mieč Šlachietny Brania"/>
  <string id="Pany2024armorlightplate1b" text="Pany of the Mieč Studded Šlachietny Brania"/>
  <string id="wotmiscplate2024type2" text="Šlachietny Płaścinavaja Brania"/>
  <string id="wotmiscplate2024type1" text="Šlachietny Płaścinavaja Brania"/>
  <string id="wotmiscboots2024type1" text="Cheaply Made Płaścinkavyja Boty"/>
  <string id="wotmisc2024shoulders2" text="Crudely Made Iron Shoulder Plates"/>
  <string id="Elfassasinarmor1" text="Siaredni Ranger Skurany"/>
  <string id="Elfassasinarmor3" text="Lohki Ranger Skurany"/>
  <string id="Elfassasinarmor2" text="Siaredni Ranger Skurany"/>
  <string id="Elfboots3" text="Brown Skurany Ranger Boty"/>
  <string id="Elfboots3b" text="Čorny Skurany Ranger Boty"/>
  <string id="Elfrangerhoodandcloak1" text="Čorny Ranger Pokryva"/>
  <string id="Elfrangerhoodandcloak2" text="Brown Ranger Pokryva"/>
  <string id="Elfrangerhoodandcloak3" text=" Ranger Pokryva"/>
  <string id="Elfrangerhoodandcloak4" text=" Grey Ranger Pokryva"/>
  <string id="Warder2024newarmor1" text="Nahladnika Navika Brania"/>
  <string id="Warder2024newarmor1b" text="Nahladnika Navika Brania"/>
  <string id="Warder2024newarmor2" text="Nahladnika Siaredniaja Brania"/>
  <string id="Warder2024newarmor22" text="Nahladnika Siaredniaja Brania"/>
  <string id="Warder2024newarmor2b" text="Nahladnika Ciažkaja Brania"/>
  <string id="Warder2024newarmor2bcheap" text="Tanny Nahladnika Ciažkaja Brania"/>
  <string id="Warder2024newboots1" text="Nahladnika Plate Skurany Boty"/>
  <string id="Miscwotbandithelm1" text="Bandit Šałom"/>
  <string id="Miscwotbandithelm1b" text="Stary Bandit Šałom"/>
  <string id="Miscwotbandithelm2" text="Bandit Lord Šałom"/>
  <string id="Miscwotbandithelm3b" text="Stary Face Šałom"/>
  <string id="Miscwotbandithelm3" text="Polished Face Šałom"/>
  <string id="Miscwotbandithelm4" text="Caged Bandit Šałom"/>
  <string id="Miscwotbandithelm4b" text="Stary Caged Bandit Šałom"/>
  <string id="ArturHawkwingshead2" text="Arthur Hawking Head"/>
  <string id="ArturHawkwingshead2play" text="Arthur Hawking Head"/>
  <string id="ArturHawkwingarmor" text="Hero of the Horn Płaścinavaja Brania"/>
  <string id="ArturHawkwingarmorplay" text="Hero of the Horn Płaścinavaja Brania"/>
  <string id="ArturHawkwingarmornew1" text="Arthur Hawking Stylovy Brania"/>
  <string id="ArturHawkwingarmornew1play" text="Arthur Hawking Stylovy Brania"/>
  <string id="ArturHawkwinggloves" text="Hero of the horn Plate Naručy"/>
  <string id="ArturHawkwingglovesnew2" text="Arthur Hawking Stylovy Naručy"/>
  <string id="ArturHawkwingglovesnew2play" text="Arthur Hawking Stylovy Naručy"/>
  <string id="ArturHawkwingscloak" text="Artur Hawkwing Pokryva"/>
  <string id="ArturHawkwingscloakplay" text="Artur Hawkwing Pokryva"/>
  <string id="ArturHawkwingbootsnew1" text="Arthur Hawking Stylovy Boty"/>
  <string id="ArturHawkwingbootsnew1play" text="Arthur Hawking Stylovy Boty"/>
  <string id="ArturHawkwingboots" text="Hero of the Horn Płaścinkavyja Boty"/>
  <string id="ArturHawkwingbootsplay" text="Hero of the Horn Płaścinkavyja Boty"/>
  <string id="Testglovesnonplayable" text="0000Testglovesnonplayables"/>
  <string id="farmadglovesmischev1" text="Golden Šlachietny Rukavicy z Skurany"/>
  <string id="Farmadmiscgloves1" text="Skurany Naručy z Steel Naručy"/>
  <string id="Farmadmiscgloves1type2" text="Skurany Naručy z Skurany Naručy"/>
  <string id="Farmadmiscgloves1type3" text="Skurany Naručy z Snakeskin Naručy"/>
  <string id="farmadmiscglovesbasic1" text="Finely Woven Šlachietny Skurany Naručy"/>
  <string id="farmadmiscglovesbasic1b" text="Patterned Thick Skurany Naručy"/>
  <string id="aethurhwakingnewshoulder" text="Artur Hawkwing Pauldrons"/>
  <string id="Hero4armor" text="Hero of the Horn Gladiator Brania"/>
  <string id="Hero4armorplay" text="Hero of the Horn Gladiator Brania"/>
  <string id="hero4helm" text="Hero of the Horn Gladiator Šałom"/>
  <string id="hero4helmplay" text="Hero of the Horn Gladiator Šałom"/>
  <string id="Hero4shoulder" text="Hero of the Horn Gladiator Pauldron"/>
  <string id="Hero4shoulderplay" text="Hero of the Horn Gladiator Pauldron"/>
  <string id="Hero4shows" text="Hero of the Horn Gladiator Boty"/>
  <string id="Hero4showsplay" text="Hero of the Horn Gladiator Boty"/>
  <string id="Hero5boots" text="Hero of the Horn Boty"/>
  <string id="Hero5bootsplay" text="Hero of the Horn Boty"/>
  <string id="Hero5chest1" text="Hero of the Horn Valkyrie Brania"/>
  <string id="Hero5chest1play" text="Hero of the Horn Valkyrie Brania"/>
  <string id="Hero6body1" text="Hero of the Horn Barbarian Brania"/>
  <string id="Hero6body1play" text="Hero of the Horn Barbarian Brania"/>
  <string id="Hero6boots" text="Hero of the Horn Barbarian Boty"/>
  <string id="Hero6bootsplay" text="Hero of the Horn Barbarian Boty"/>
  <string id="hero5helm" text="Hero of the Horn Valkyrie Helm"/>
  <string id="hero5helmplay" text="Hero of the Horn Valkyrie Helm"/>
  <string id="Hero8armor1" text="Hero of the Horn Miyo Brania"/>
  <string id="Hero8armor1play" text="Hero of the Horn Miyo Brania"/>
  <string id="Hero8armorboots1" text="Hero of the Horn Miyo Boty"/>
  <string id="Hero8armorboots1play" text="Hero of the Horn Miyo Boty"/>
  <string id="Heroesarmortype2" text="Hero of the Horn Scale and Plate"/>
  <string id="Heroesarmortype2play" text="Hero of the Horn Scale and Plate"/>
  <string id="Heroesarmortype3play" text="Hero of the Horn Sea Dog Brania"/>
  <string id="Heroestype3bootsplay" text="Hero of the Horn Sea Dog Boty"/>
  <string id="Heroestype3boots" text="Hero of the Horn Sea Dog Boty"/>
  <string id="Heroetype3hat" text="Hero of the Horn Sea Dog Kapialuch"/>
  <string id="Heroetype3hatplay" text="Hero of the Horn Sea Dog Kapialuch"/>
  <string id="Miscwotheadnew1" text="Saldea Skurany Horse Šałom"/>
  <string id="Miscwotheadnew1cheap" text="Saldea Tanny Skurany Horse Šałom"/>
  <string id="Miscwotheadnew2heavy1" text="Studded leather Plate Rukavicy"/>
  <string id="Miscwotheadnew2heavy1b" text="Patched Steel Plate Rukavicy"/>
  <string id="Miscwotheadnew2heavy1c" text="Łancuhova-Kalčužny Steel Plate Rukavicy"/>
  <string id="Miscwotheadnew2heavy1d" text="Łancuhova-Kalčužny Steel Plate Rukavicy Varient"/>
  <string id="Miscwotheadnew2heavy1e" text="Gamberson Steel Plate Rukavicy"/>
  <string id="Miscwotheadnew2heavy1f" text="Patched Cloth Steel Plate Rukavicy"/>
  <string id="Miscwotheadnew2heavy2" text="Studded Skurany Steel Plate Rukavicy Varient"/>
  <string id="Miscwotheadnew2heavy2d" text="Patched Cloth Plate Rukavicy Varient 2"/>
  <string id="Miscwotheadnew2heavy2e" text="Łancuhova-Kalčužny Plate Rukavicy Varient 2"/>
  <string id="Miscwotheadnew2heavy2f" text="Gamberson Plate Rukavicy Varient 2"/>
  <string id="Miscwotheadnew2light" text="Studded Skurany Naručy"/>
  <string id="Miscwotheadnew2lightd" text="Gamberson Naručy"/>
  <string id="Miscwotheadnew2lighte" text="Patched Cloth Naručy"/>
  <string id="Miscwotheadnew2lightf" text="Łancuhova-Kalčužny Naručy"/>
  <string id="Miscwotbanditarmor1" text="Studded Ciažki Skurany z Chestpiece"/>
  <string id="Miscwotbanditarmor1b" text="Studded Legs Ciažki Skurany Chestpiece Varient"/>
  <string id="Miscwotbanditarmor2" text="Studded Ciažki Skurany Chestpiece Varient"/>
  <string id="Miscwotbanditarmor2b" text="Studded Legs Ciažki Skurany Chestpiece Varient"/>
  <string id="wotmiscpurgloves1" text="Reinforced Gamberson Naručy"/>
  <string id="wotmiscpurgloves10" text="Stitched Skurany Naručy"/>
  <string id="wotmiscpurgloves11" text="Fine Studded Skurany Naručy"/>
  <string id="wotmiscpurgloves12" text="Fine Reinforced Skurany Naručy"/>
  <string id="wotmiscpurgloves13" text="Tanny Reinforced Skurany Naručy"/>
  <string id="wotmiscpurgloves2" text="Reinforced Gamberson Naručy Varient"/>
  <string id="wotmiscpurgloves5" text="Hruntoŭny Skurany Naručy"/>
  <string id="wotmiscpurgloves4" text="Fine Reinforced Hruntoŭny Skurany Naručy"/>
  <string id="wotmiscpurgloves3" text="Fine Skurany Naručy z Steel Reinforcement"/>
  <string id="wotmiscpurgloves3cheap" text="Tanny Naručy z Steel Reinforcement"/>
  <string id="wotmiscpurgloves6" text="Fine Skurany Plate Naručy"/>
  <string id="wotmiscpurgloves7" text="Fine Šlachietny Skurany Strapped Naručy"/>
  <string id="wotmiscpurgloves8" text="Skurany Woven Naručy"/>
  <string id="wotmiscpurgloves9" text="Fine Šlachietny Studded Naručy"/>
  <string id="wotmiscpurshoulders1" text="Decorated Fine Skurany Shoulders"/>
  <string id="wotmiscpurshoulders2" text="Studded Skurany Shoulders"/>
  <string id="Wot2024horsearmor1" text="Fine Skurany Horse Brania"/>
  <string id="Wot2024horsearmor10" text="Patched Steel Horse Brania"/>
  <string id="Wot2024horsearmor11" text="Thick Skurany Horse Brania"/>
  <string id="Wot2024horsearmor14" text="Arafel Horse Coat With Mail"/>
  <string id="Wot2024horsearmor15" text="Arafel Plated Horse Brania With Mail"/>
  <string id="Wot2024horsearmor13" text="Illian Lohki Horse Coat"/>
  <string id="Wot2024horsearmor3" text="Illian Scale Plate Painted Horse Brania"/>
  <string id="Wot2024horsearmor4" text="Ring Plate Horse Brania"/>
  <string id="Wot2024horsearmor2" text="Andorski Horse Coat"/>
  <string id="Wot2024horsearmor5" text="Andorski Ring Plate Horse Brania"/>
  <string id="Wot2024horsearmor6" text="Cairhien Ciažki Cloth Horse Coat"/>
  <string id="Wot2024horsearmor7" text="Cairhien Painted Mail Horse Coat"/>
  <string id="Wot2024horsearmor8" text="Cairhien Plate Horse Brania"/>
  <string id="wothorseset5misc1" text="Saldea Skurany Horse Brania"/>
  <string id="Wot2024horsearmor9" text="Saldea Steel Plate Horse Brania and Mail"/>
  <string id="Wot2024horsearmor12" text="Saldea Fused Plates Horse Brania"/>
  <string id="wothorseset5misc2b" text="Saldea Skurany Horse Brania"/>
  <string id="wothorseset5misc2" text="Worn Miakki Horse Brania"/>
  <string id="wothorseset5multi1" text="Shienar Reinforced Skurany Horse Brania"/>
  <string id="wothorseset5multi4" text="Shienar Thick Skurany Horse Brania"/>
  <string id="wothorseset5multi8" text="Shienar Skurany Horse Brania With Steel Reinforcement"/>
  <string id="wothorseset5multi2" text="Cirski Fine Skurany Horse Brania"/>
  <string id="wothorseset5multi5" text="Thick Skurany Horse Brania"/>
  <string id="wothorseset5multi6" text="Thick Skurany Horse Brania"/>
  <string id="wothorseset5multi7" text="Thick Skurany Horse Brania"/>
  <string id="wothorseset5multi3" text=" Horse Gamberson Brania"/>
  <string id="wotmiscpurarmor1" text="Reinforced Skurany Chestpiece"/>
  <string id="wotmiscpurarmor1b" text="Reinforced Skurany Mail Chestpiece"/>
  <string id="Miscwotheadnew2lightb" text="Patched Steel Naručy"/>
  <string id="Miscwotheadnew2lightc" text="Patched Steel Naručy Varient"/>
  <string id="Miscwotheadnew2heavy2b" text="Patched Steel Plate Rukavicy Varient"/>
  <string id="Miscwotheadnew2heavy2c" text="Patched Steel Plate Rukavicy Varient 2"/>
  <string id="Wot2024horsearmorse1" text=" Seanchan Lohki Horse Brania"/>
  <string id="Wot2024horsearmorse2" text=" Seanchan Ciažki Horse Brania"/>
  <string id="Wot2024horsearmorwc1" text=" Biełych Pokryvaŭ Lohki Horse Brania"/>
  <string id="Wot2024horsearmorwc2" text=" Biełych Pokryvaŭ Ciažki Horse Brania"/>
  <string id="wot2024whitecloakarmor1" text="Biełych Pokryvaŭ Polished Płaścinavaja Brania"/>
  <string id="wot2024whitecloakarmor2" text="Biełych Pokryvaŭ Polished Płaścinavaja Brania"/>
  <string id="wot2024whitecloakarmor3" text="Biełych Pokryvaŭ Polished Płaścinavaja Brania z Mail"/>
  <string id="wot2024whitecloakboots1" text="Polished Biełych Pokryvaŭ Boty"/>
  <string id="wot2024whitecloakgloves1" text="Biełych Pokryvaŭ Šlachietny Naručy"/>
  <string id="wot2024whitecloakgloves2" text="Biełych Pokryvaŭ Miakki Naručy"/>
  <string id="wot2024whitecloakgloves3" text="Biełych Pokryvaŭ Łancuhova-Kalčužny Naručy"/>
  <string id="wot2024whitecloakhelm1" text="Biełych Pokryvaŭ Polished Ciažki Šałom"/>
  <string id="onepowertest" text="00000powwertest1"/>
  <string id="B_silverbow1" text="Birgittes Silverbow"/>
  <string id="B_silverbowarr1" text="Birgittes Streły"/>
  <string id="TwoRiversArcher1hero" text="Hero of the Horn Archer Brania"/>
  <string id="TwoRivers_ArcherHoodhero" text="Hero of the Horn Archer Hood"/>
  <string id="WarderarmorLightoldStylovy" text="Nahladnika Stary Stylovy Brania"/>
  <string id="WarderArmorMediumweakold" text="Nahladnika Stary Stylovy Navika Brania"/>
  <string id="WarderArmorMediumold" text="Nahladnika Stary Stylovy Siaredniaja Brania"/>
  <string id="WarderHeavyArmorold" text="Nahladnika Stary Stylovy Ciažkaja Brania"/>
  <string id="wot2024whitecloakarmor1cheap" text="Tanny Biełych Pokryvaŭ Polished Płaścinavaja Brania"/>
  <string id="wot2024whitecloakboots1cheap" text="Tanny Polished Biełych Pokryvaŭ Boty"/>
  <string id="wot2024whitecloakgloves2cheap" text="Tanny Biełych Pokryvaŭ Miakki Naručy"/>
  <string id="wot2024whitecloakhelm1cheap" text="Tanny Biełych Pokryvaŭ Polished Ciažki Šałom"/>
  <string id="wot2024shieldnew1" text="Ornamental Mietaličny Ščyt"/>
  <string id="wot2024shieldnew2" text="Ornamental Mietaličny Ščyt"/>
  <string id="wot2024shieldnew3" text="Ornamental Mietaličny Ščyt"/>
  <string id="wot2024shieldnewkite1" text="Ornamental Kite Ščyt"/>
  <string id="wot2024shieldnewkite2" text="Ornamental Kite Ščyt"/>
 </strings>
</base>